require.py
flask_require-0.0.5.dist-info/LICENSE
flask_require-0.0.5.dist-info/METADATA
flask_require-0.0.5.dist-info/WHEEL
flask_require-0.0.5.dist-info/top_level.txt
flask_require-0.0.5.dist-info/RECORD
