Metadata-Version: 2.1
Name: flask-require
Version: 0.0.5
Summary: A simple Flask extension for requiring parameters in a request.
Author-email: Ivar Jönsson <ivajns-9@student.ltu.se>
License: MIT License
Project-URL: repository, https://github.com/ivario123/flask_require
Project-URL: source, https://github.com/ivario123/flask_require
License-File: LICENSE
Requires-Dist: flask (>=0.10.1)
